talkback/__init__.py
talkback/app.py
talkback/cookie.py
talkback/dbkeeper.py
talkback/formdata.py
talkback/fskeeper.py
talkback/loader.py
talkback/parse.py
talkback/path.py
talkback/responder.py
talkback/session.py
talkback/transport.py
talkback-1.5.dist-info/METADATA
talkback-1.5.dist-info/WHEEL
talkback-1.5.dist-info/top_level.txt
talkback-1.5.dist-info/RECORD
